setup.py
cms/__init__.py
cms/admin.py
cms/models.py
cms/migrations/0001_initial.py
cms/migrations/__init__.py
montanha/__init__.py
montanha/admin.py
montanha/cnpj.py
montanha/consolidatedmodels.py
montanha/cpf.py
montanha/forms.py
montanha/models.py
montanha/urls.py
montanha/util.py
montanha/views.py
montanha/management/__init__.py
montanha/management/commands/__init__.py
montanha/management/commands/collect.py
montanha/management/commands/collect_images.py
montanha/management/commands/consolidate.py
montanha/management/commands/supplier_address.py
montanha/management/commands/collectors/__init__.py
montanha/management/commands/collectors/algo.py
montanha/management/commands/collectors/almg.py
montanha/management/commands/collectors/basecollector.py
montanha/management/commands/collectors/cdep.py
montanha/management/commands/collectors/cmbh.py
montanha/management/commands/collectors/cmsp.py
montanha/management/commands/collectors/senado.py
montanha/management/commands/tests/__init__.py
montanha/management/commands/tests/test_collect.py
montanha/migrations/0001_initial.py
montanha/migrations/0002_auto__add_field_legislator_site__add_field_legislator_email__add_field.py
montanha/migrations/0003_auto__add_collectionrun__add_archivedexpense.py
montanha/migrations/0004_archived_expenses.py
montanha/migrations/0005_auto__add_field_legislature_original_id.py
montanha/migrations/0006_merge_0003_through_0005.py
montanha/migrations/0007_auto__add_pernaturebyyear__add_pernature.py
montanha/migrations/0008_auto__add_pernaturebymonth.py
montanha/migrations/0009_auto__add_perlegislator.py
montanha/migrations/0010_auto__add_biggestsupplierforyear.py
montanha/migrations/0011_auto__add_alternativelegislatorname__del_field_legislator_original_id.py
montanha/migrations/0012_auto__add_field_mandate_original_id.py
montanha/migrations/0013_auto__add_field_mandate_state.py
montanha/migrations/0014_auto__chg_field_pernaturebyyear_expensed__chg_field_pernature_expensed.py
olhoneles.egg-info/PKG-INFO
olhoneles.egg-info/SOURCES.txt
olhoneles.egg-info/dependency_links.txt
olhoneles.egg-info/requires.txt
olhoneles.egg-info/top_level.txt