Metadata-Version: 1.1
Name: olhoneles
Version: 0.1.29
Summary: Activities of the Brazilian legislators
Home-page: http://olhoneles.org
Author: OlhoNeles.org
Author-email: montanha@olhoneles.org
License: AGPL
Keywords: brazilian legislators web
Platform: UNKNOWN
Classifier: Development Status :: 4 - Beta
Classifier: Intended Audience :: Developers
Classifier: License :: OSI Approved :: GNU Affero General Public License v3 or later (AGPLv3+)
Classifier: Natural Language :: English
Classifier: Operating System :: POSIX :: Linux
Classifier: Operating System :: OS Independent
Classifier: Programming Language :: Python :: 2.7
Classifier: Topic :: Internet :: WWW/HTTP :: Dynamic Content
